Metadata-Version: 2.4
Name: cursofiap-package-isabelpt
Version: 1.0.0
Summary: Descricao da sua lib cursofiap
Home-page: https://github.com/isabelapt/cursofiap
Author: Isabela P Trindade
Author-email: isabelatrindade94@hotmail.com
License: MIT
Dynamic: author
Dynamic: author-email
Dynamic: description
Dynamic: description-content-type
Dynamic: home-page
Dynamic: license
Dynamic: summary
